[ {
  "login" : "Petya",
  "password" : "petya@gmail.com",
  "websites" : {
    "youtube" : {
      "credentials" : [ {
        "login" : "login",
        "password" : "password"
      } ]
    },
    "github" : {
      "credentials" : [ {
        "login" : "login",
        "password" : "password"
      } ]
    },
    "google" : {
      "credentials" : [ {
        "login" : "login",
        "password" : "password"
      } ]
    }
  }
}, {
  "login" : "Vasya",
  "password" : "vasya@gmail.com",
  "websites" : {
    "youtube" : {
      "credentials" : [ {
        "login" : "login",
        "password" : "password"
      } ]
    },
    "github" : {
      "credentials" : [ {
        "login" : "login",
        "password" : "password"
      } ]
    },
    "google" : {
      "credentials" : [ {
        "login" : "login",
        "password" : "password"
      } ]
    }
  }
} ]